privacy_similarity/__init__.py
privacy_similarity/core.py
privacy_similarity/utils.py
privacy_similarity/blocking/__init__.py
privacy_similarity/blocking/clustering.py
privacy_similarity/blocking/lsh.py
privacy_similarity/embeddings/__init__.py
privacy_similarity/embeddings/numeric_features.py
privacy_similarity/embeddings/text_embeddings.py
privacy_similarity/privacy/__init__.py
privacy_similarity/privacy/differential_privacy.py
privacy_similarity/privacy/homomorphic.py
privacy_similarity/privacy/secure_hash.py
privacy_similarity/search/__init__.py
privacy_similarity/search/faiss_index.py
privacy_similarity/search/similarity.py
privacy_similarity-0.1.4.dist-info/licenses/LICENSE
privacy_similarity-0.1.4.dist-info/METADATA
privacy_similarity-0.1.4.dist-info/WHEEL
privacy_similarity-0.1.4.dist-info/top_level.txt
privacy_similarity-0.1.4.dist-info/RECORD
