Metadata-Version: 2.4
Name: privacy-similarity
Version: 0.1.4
Summary: Privacy-preserving similarity search for massive DataFrames with PII
Home-page: https://github.com/alexandernicholson/python-similarity
Author: Alexander Nicholson
License-Expression: MIT
Project-URL: Homepage, https://github.com/alexandernicholson/python-similarity
Project-URL: Documentation, https://github.com/alexandernicholson/python-similarity/tree/main/docs
Project-URL: Repository, https://github.com/alexandernicholson/python-similarity
Project-URL: Issues, https://github.com/alexandernicholson/python-similarity/issues
Project-URL: Changelog, https://github.com/alexandernicholson/python-similarity/blob/main/CHANGELOG.md
Keywords: privacy,similarity-search,differential-privacy,pii,embeddings,faiss,deduplication
Classifier: Development Status :: 3 - Alpha
Classifier: Intended Audience :: Developers
Classifier: Intended Audience :: Science/Research
Classifier: Topic :: Scientific/Engineering :: Artificial Intelligence
Classifier: Topic :: Security :: Cryptography
Classifier: Programming Language :: Python :: 3
Classifier: Programming Language :: Python :: 3.8
Classifier: Programming Language :: Python :: 3.9
Classifier: Programming Language :: Python :: 3.10
Classifier: Programming Language :: Python :: 3.11
Requires-Python: >=3.8
License-File: LICENSE
Requires-Dist: numpy>=1.20.0
Requires-Dist: pandas>=1.3.0
Requires-Dist: scikit-learn>=1.0.0
Requires-Dist: sentence-transformers>=2.2.0
Requires-Dist: faiss-cpu>=1.7.0
Requires-Dist: pycryptodome>=3.15.0
Requires-Dist: mmh3>=3.0.0
Provides-Extra: gpu
Requires-Dist: faiss-gpu>=1.7.4; extra == "gpu"
Provides-Extra: dev
Requires-Dist: pytest>=7.0.0; extra == "dev"
Requires-Dist: pytest-cov>=3.0.0; extra == "dev"
Requires-Dist: black>=22.0.0; extra == "dev"
Requires-Dist: flake8>=4.0.0; extra == "dev"
Requires-Dist: mypy>=0.950; extra == "dev"
Requires-Dist: bump2version>=1.0.0; extra == "dev"
Requires-Dist: build>=0.7.0; extra == "dev"
Requires-Dist: twine>=4.0.0; extra == "dev"
Dynamic: home-page
Dynamic: license-file
Dynamic: requires-python
